{
    "Nom": "Ile-de-France",
    "Evolution" :[
 {
  "Region": "IledeFrance",
  "Date": "2013-1",
  "Consommation": 16826536,
  "Production": 1706757,
  "Thermique": 1511681,
  "Nucleaire": 0,
  "Eolien": 5861,
  "Solaire": 1614,
  "Hydraulique": 86,
  "BioEnergie": 187515
 },
 {
  "Region": "IledeFrance",
  "Date": "2013-2",
  "Consommation": 32439985,
  "Production": 3234351,
  "Thermique": 2854430,
  "Nucleaire": 0,
  "Eolien": 12650,
  "Solaire": 5865,
  "Hydraulique": 94,
  "BioEnergie": 361312
 },
 {
  "Region": "IledeFrance",
  "Date": "2013-3",
  "Consommation": 48022481,
  "Production": 4973707,
  "Thermique": 4398563,
  "Nucleaire": 0,
  "Eolien": 17905,
  "Solaire": 13384,
  "Hydraulique": 6081,
  "BioEnergie": 537774
 },
 {
  "Region": "IledeFrance",
  "Date": "2013-4",
  "Consommation": 60480289,
  "Production": 5549489,
  "Thermique": 4794717,
  "Nucleaire": 0,
  "Eolien": 24381,
  "Solaire": 25777,
  "Hydraulique": 13623,
  "BioEnergie": 690991
 },
 {
  "Region": "IledeFrance",
  "Date": "2013-5",
  "Consommation": 71629876,
  "Production": 5824506,
  "Thermique": 4879420,
  "Nucleaire": 0,
  "Eolien": 28873,
  "Solaire": 39036,
  "Hydraulique": 13853,
  "BioEnergie": 863324
 },
 {
  "Region": "IledeFrance",
  "Date": "2013-6",
  "Consommation": 81616848,
  "Production": 6202938,
  "Thermique": 5065819,
  "Nucleaire": 0,
  "Eolien": 33408,
  "Solaire": 53675,
  "Hydraulique": 19933,
  "BioEnergie": 1030103
 },
 {
  "Region": "IledeFrance",
  "Date": "2013-7",
  "Consommation": 91642362,
  "Production": 6618686,
  "Thermique": 5231620,
  "Nucleaire": 0,
  "Eolien": 37545,
  "Solaire": 72154,
  "Hydraulique": 32979,
  "BioEnergie": 1244388
 },
 {
  "Region": "IledeFrance",
  "Date": "2013-8",
  "Consommation": 100517348,
  "Production": 7020112,
  "Thermique": 5415073,
  "Nucleaire": 0,
  "Eolien": 40305,
  "Solaire": 87830,
  "Hydraulique": 43036,
  "BioEnergie": 1433868
 },
 {
  "Region": "IledeFrance",
  "Date": "2013-9",
  "Consommation": 110469782,
  "Production": 7598178,
  "Thermique": 5824918,
  "Nucleaire": 0,
  "Eolien": 44341,
  "Solaire": 98265,
  "Hydraulique": 52446,
  "BioEnergie": 1578208
 },
 {
  "Region": "IledeFrance",
  "Date": "2013-10",
  "Consommation": 121875888,
  "Production": 8211876,
  "Thermique": 6229459,
  "Nucleaire": 0,
  "Eolien": 51123,
  "Solaire": 105177,
  "Hydraulique": 59581,
  "BioEnergie": 1766536
 },
 {
  "Region": "IledeFrance",
  "Date": "2013-11",
  "Consommation": 136028729,
  "Production": 9318129,
  "Thermique": 7149902,
  "Nucleaire": 0,
  "Eolien": 59527,
  "Solaire": 108465,
  "Hydraulique": 59620,
  "BioEnergie": 1940615
 },
 {
  "Region": "IledeFrance",
  "Date": "2013-12",
  "Consommation": 151410004,
  "Production": 10423671,
  "Thermique": 8037750,
  "Nucleaire": 0,
  "Eolien": 69062,
  "Solaire": 112202,
  "Hydraulique": 63775,
  "BioEnergie": 2140882
 },
 {
  "Region": "IledeFrance",
  "Date": "2013",
  "Consommation": 1022960128,
  "Production": 76682400,
  "Thermique": 61393352,
  "Nucleaire": 0,
  "Eolien": 424981,
  "Solaire": 723444,
  "Hydraulique": 365107,
  "BioEnergie": 13775516
 },
 {
  "Region": "IledeFrance",
  "Date": "2014-1",
  "Consommation": 166668339,
  "Production": 11343010,
  "Thermique": 8709228,
  "Nucleaire": 0,
  "Eolien": 79957,
  "Solaire": 115299,
  "Hydraulique": 67416,
  "BioEnergie": 2371110
 },
 {
  "Region": "IledeFrance",
  "Date": "2014-2",
  "Consommation": 180199267,
  "Production": 11964159,
  "Thermique": 9087353,
  "Nucleaire": 0,
  "Eolien": 92983,
  "Solaire": 121167,
  "Hydraulique": 68873,
  "BioEnergie": 2593783
 },
 {
  "Region": "IledeFrance",
  "Date": "2014-3",
  "Consommation": 193255216,
  "Production": 12789096,
  "Thermique": 9648737,
  "Nucleaire": 0,
  "Eolien": 98724,
  "Solaire": 134301,
  "Hydraulique": 77173,
  "BioEnergie": 2830161
 },
 {
  "Region": "IledeFrance",
  "Date": "2014-4",
  "Consommation": 204059737,
  "Production": 13196841,
  "Thermique": 9810350,
  "Nucleaire": 0,
  "Eolien": 102759,
  "Solaire": 148105,
  "Hydraulique": 90905,
  "BioEnergie": 3044722
 },
 {
  "Region": "IledeFrance",
  "Date": "2014-5",
  "Consommation": 214628608,
  "Production": 13548837,
  "Thermique": 9910227,
  "Nucleaire": 0,
  "Eolien": 109764,
  "Solaire": 164737,
  "Hydraulique": 102503,
  "BioEnergie": 3261606
 },
 {
  "Region": "IledeFrance",
  "Date": "2014-6",
  "Consommation": 224264987,
  "Production": 13839631,
  "Thermique": 10011057,
  "Nucleaire": 0,
  "Eolien": 114390,
  "Solaire": 183529,
  "Hydraulique": 109519,
  "BioEnergie": 3421136
 },
 {
  "Region": "IledeFrance",
  "Date": "2014-7",
  "Consommation": 234051901,
  "Production": 14085886,
  "Thermique": 10022750,
  "Nucleaire": 0,
  "Eolien": 118337,
  "Solaire": 199312,
  "Hydraulique": 116466,
  "BioEnergie": 3629021
 },
 {
  "Region": "IledeFrance",
  "Date": "2014-8",
  "Consommation": 242769004,
  "Production": 14313634,
  "Thermique": 10030327,
  "Nucleaire": 0,
  "Eolien": 122525,
  "Solaire": 214344,
  "Hydraulique": 126788,
  "BioEnergie": 3819650
 },
 {
  "Region": "IledeFrance",
  "Date": "2014-9",
  "Consommation": 252523853,
  "Production": 14735371,
  "Thermique": 10259482,
  "Nucleaire": 0,
  "Eolien": 125651,
  "Solaire": 229113,
  "Hydraulique": 136031,
  "BioEnergie": 3985094
 },
 {
  "Region": "IledeFrance",
  "Date": "2014-10",
  "Consommation": 263624046,
  "Production": 15322772,
  "Thermique": 10614681,
  "Nucleaire": 0,
  "Eolien": 130852,
  "Solaire": 237275,
  "Hydraulique": 147896,
  "BioEnergie": 4192068
 },
 {
  "Region": "IledeFrance",
  "Date": "2014-11",
  "Consommation": 276162524,
  "Production": 16192654,
  "Thermique": 11258835,
  "Nucleaire": 0,
  "Eolien": 136206,
  "Solaire": 241737,
  "Hydraulique": 159476,
  "BioEnergie": 4396400
 },
 {
  "Region": "IledeFrance",
  "Date": "2014-12",
  "Consommation": 291891899,
  "Production": 17403341,
  "Thermique": 12227690,
  "Nucleaire": 0,
  "Eolien": 144745,
  "Solaire": 244042,
  "Hydraulique": 168101,
  "BioEnergie": 4618763
 },
 {
  "Region": "IledeFrance",
  "Date": "2014",
  "Consommation": 4790019637,
  "Production": 322100032,
  "Thermique": 244377421,
  "Nucleaire": 0,
  "Eolien": 2226855,
  "Solaire": 3679849,
  "Hydraulique": 2101361,
  "BioEnergie": 69714546
 },
 {
  "Region": "IledeFrance",
  "Date": "2015-1",
  "Consommation": 308284432,
  "Production": 18605436,
  "Thermique": 13225217,
  "Nucleaire": 0,
  "Eolien": 154618,
  "Solaire": 247099,
  "Hydraulique": 172117,
  "BioEnergie": 4806385
 },
 {
  "Region": "IledeFrance",
  "Date": "2015-2",
  "Consommation": 323169399,
  "Production": 19977784,
  "Thermique": 14414546,
  "Nucleaire": 0,
  "Eolien": 163055,
  "Solaire": 253252,
  "Hydraulique": 176640,
  "BioEnergie": 4970291
 },
 {
  "Region": "IledeFrance",
  "Date": "2015-3",
  "Consommation": 337320552,
  "Production": 21164699,
  "Thermique": 15400587,
  "Nucleaire": 0,
  "Eolien": 170684,
  "Solaire": 264119,
  "Hydraulique": 184972,
  "BioEnergie": 5144337
 },
 {
  "Region": "IledeFrance",
  "Date": "2015-4",
  "Consommation": 348422094,
  "Production": 21472747,
  "Thermique": 15511191,
  "Nucleaire": 0,
  "Eolien": 176588,
  "Solaire": 280558,
  "Hydraulique": 194830,
  "BioEnergie": 5309580
 },
 {
  "Region": "IledeFrance",
  "Date": "2015-5",
  "Consommation": 358747953,
  "Production": 21675172,
  "Thermique": 15539349,
  "Nucleaire": 0,
  "Eolien": 182168,
  "Solaire": 298005,
  "Hydraulique": 201670,
  "BioEnergie": 5453980
 },
 {
  "Region": "IledeFrance",
  "Date": "2015-6",
  "Consommation": 368541514,
  "Production": 21887984,
  "Thermique": 15565184,
  "Nucleaire": 0,
  "Eolien": 186613,
  "Solaire": 319418,
  "Hydraulique": 213704,
  "BioEnergie": 5603065
 },
 {
  "Region": "IledeFrance",
  "Date": "2015-7",
  "Consommation": 378364114,
  "Production": 22102382,
  "Thermique": 15593427,
  "Nucleaire": 0,
  "Eolien": 191858,
  "Solaire": 339028,
  "Hydraulique": 220790,
  "BioEnergie": 5757279
 },
 {
  "Region": "IledeFrance",
  "Date": "2015-8",
  "Consommation": 387250814,
  "Production": 22326620,
  "Thermique": 15603404,
  "Nucleaire": 0,
  "Eolien": 198489,
  "Solaire": 356509,
  "Hydraulique": 228860,
  "BioEnergie": 5939358
 },
 {
  "Region": "IledeFrance",
  "Date": "2015-9",
  "Consommation": 397177102,
  "Production": 22554388,
  "Thermique": 15620088,
  "Nucleaire": 0,
  "Eolien": 211490,
  "Solaire": 370557,
  "Hydraulique": 240508,
  "BioEnergie": 6111745
 },
 {
  "Region": "IledeFrance",
  "Date": "2015-10",
  "Consommation": 409277694,
  "Production": 22828310,
  "Thermique": 15673382,
  "Nucleaire": 0,
  "Eolien": 219060,
  "Solaire": 379004,
  "Hydraulique": 252699,
  "BioEnergie": 6304165
 },
 {
  "Region": "IledeFrance",
  "Date": "2015-11",
  "Consommation": 421802101,
  "Production": 23756589,
  "Thermique": 16383552,
  "Nucleaire": 0,
  "Eolien": 235572,
  "Solaire": 383926,
  "Hydraulique": 263457,
  "BioEnergie": 6490082
 },
 {
  "Region": "IledeFrance",
  "Date": "2015-12",
  "Consommation": 435383988,
  "Production": 24658313,
  "Thermique": 17050803,
  "Nucleaire": 0,
  "Eolien": 249934,
  "Solaire": 387908,
  "Hydraulique": 278268,
  "BioEnergie": 6691400
 },
 {
  "Region": "IledeFrance",
  "Date": "2015",
  "Consommation": 14053781031,
  "Production": 907210488,
  "Thermique": 674335572,
  "Nucleaire": 0,
  "Eolien": 6793839,
  "Solaire": 11239081,
  "Hydraulique": 6831237,
  "BioEnergie": 208010759
 },
 {
  "Region": "IledeFrance",
  "Date": "2016-1",
  "Consommation": 450981365,
  "Production": 25615935,
  "Thermique": 17763589,
  "Nucleaire": 0,
  "Eolien": 268021,
  "Solaire": 391548,
  "Hydraulique": 294106,
  "BioEnergie": 6898671
 },
 {
  "Region": "IledeFrance",
  "Date": "2016-2",
  "Consommation": 465230708,
  "Production": 26520193,
  "Thermique": 18440195,
  "Nucleaire": 0,
  "Eolien": 286667,
  "Solaire": 398107,
  "Hydraulique": 297204,
  "BioEnergie": 7098020
 },
 {
  "Region": "IledeFrance",
  "Date": "2016-3",
  "Consommation": 479747879,
  "Production": 27406524,
  "Thermique": 19079202,
  "Nucleaire": 0,
  "Eolien": 303265,
  "Solaire": 408563,
  "Hydraulique": 304588,
  "BioEnergie": 7310906
 },
 {
  "Region": "IledeFrance",
  "Date": "2016-4",
  "Consommation": 491649242,
  "Production": 27676212,
  "Thermique": 19148559,
  "Nucleaire": 0,
  "Eolien": 312764,
  "Solaire": 423568,
  "Hydraulique": 315156,
  "BioEnergie": 7476165
 },
 {
  "Region": "IledeFrance",
  "Date": "2016-5",
  "Consommation": 502194601,
  "Production": 27961102,
  "Thermique": 19198431,
  "Nucleaire": 0,
  "Eolien": 321180,
  "Solaire": 438840,
  "Hydraulique": 327867,
  "BioEnergie": 7674784
 },
 {
  "Region": "IledeFrance",
  "Date": "2016-6",
  "Consommation": 512086605,
  "Production": 28213308,
  "Thermique": 19236424,
  "Nucleaire": 0,
  "Eolien": 326862,
  "Solaire": 453315,
  "Hydraulique": 327911,
  "BioEnergie": 7868796
 },
 {
  "Region": "IledeFrance",
  "Date": "2016-7",
  "Consommation": 521600634,
  "Production": 28531168,
  "Thermique": 19265463,
  "Nucleaire": 0,
  "Eolien": 332346,
  "Solaire": 472625,
  "Hydraulique": 338979,
  "BioEnergie": 8121755
 },
 {
  "Region": "IledeFrance",
  "Date": "2016-8",
  "Consommation": 530499574,
  "Production": 28782871,
  "Thermique": 19286035,
  "Nucleaire": 0,
  "Eolien": 339140,
  "Solaire": 490912,
  "Hydraulique": 348732,
  "BioEnergie": 8318052
 },
 {
  "Region": "IledeFrance",
  "Date": "2016-9",
  "Consommation": 540141007,
  "Production": 29115256,
  "Thermique": 19389468,
  "Nucleaire": 0,
  "Eolien": 343853,
  "Solaire": 503652,
  "Hydraulique": 358797,
  "BioEnergie": 8519486
 },
 {
  "Region": "IledeFrance",
  "Date": "2016-10",
  "Consommation": 551896700,
  "Production": 29655917,
  "Thermique": 19689587,
  "Nucleaire": 0,
  "Eolien": 352508,
  "Solaire": 518241,
  "Hydraulique": 368702,
  "BioEnergie": 8726879
 },
 {
  "Region": "IledeFrance",
  "Date": "2016-11",
  "Consommation": 565622166,
  "Production": 30929402,
  "Thermique": 20720385,
  "Nucleaire": 0,
  "Eolien": 365907,
  "Solaire": 522924,
  "Hydraulique": 380039,
  "BioEnergie": 8940147
 },
 {
  "Region": "IledeFrance",
  "Date": "2016-12",
  "Consommation": 581432044,
  "Production": 32172011,
  "Thermique": 21709214,
  "Nucleaire": 0,
  "Eolien": 371667,
  "Solaire": 527086,
  "Hydraulique": 394171,
  "BioEnergie": 9169873
 },
 {
  "Region": "IledeFrance",
  "Date": "2016",
  "Consommation": 34300644587,
  "Production": 2157000875,
  "Thermique": 1581597696,
  "Nucleaire": 0,
  "Eolien": 17511858,
  "Solaire": 28027543,
  "Hydraulique": 17718726,
  "BioEnergie": 512145052
 },
 {
  "Region": "IledeFrance",
  "Date": "2017-1",
  "Consommation": 599217790,
  "Production": 34055513,
  "Thermique": 23348660,
  "Nucleaire": 0,
  "Eolien": 381937,
  "Solaire": 531121,
  "Hydraulique": 408837,
  "BioEnergie": 9384958
 },
 {
  "Region": "IledeFrance",
  "Date": "2017-2",
  "Consommation": 612555659,
  "Production": 35010117,
  "Thermique": 24066723,
  "Nucleaire": 0,
  "Eolien": 396294,
  "Solaire": 536314,
  "Hydraulique": 424173,
  "BioEnergie": 9586613
 },
 {
  "Region": "IledeFrance",
  "Date": "2017-3",
  "Consommation": 625453725,
  "Production": 35860469,
  "Thermique": 24681440,
  "Nucleaire": 0,
  "Eolien": 416136,
  "Solaire": 547157,
  "Hydraulique": 433778,
  "BioEnergie": 9781958
 },
 {
  "Region": "IledeFrance",
  "Date": "2017-4",
  "Consommation": 636397469,
  "Production": 36113256,
  "Thermique": 24690253,
  "Nucleaire": 0,
  "Eolien": 425616,
  "Solaire": 564932,
  "Hydraulique": 447545,
  "BioEnergie": 9984910
 },
 {
  "Region": "IledeFrance",
  "Date": "2017-5",
  "Consommation": 646820547,
  "Production": 36365137,
  "Thermique": 24705375,
  "Nucleaire": 0,
  "Eolien": 435967,
  "Solaire": 585296,
  "Hydraulique": 457276,
  "BioEnergie": 10181223
 },
 {
  "Region": "IledeFrance",
  "Date": "2017-6",
  "Consommation": 656470883,
  "Production": 36658337,
  "Thermique": 24743092,
  "Nucleaire": 0,
  "Eolien": 446054,
  "Solaire": 607536,
  "Hydraulique": 463771,
  "BioEnergie": 10397884
 },
 {
  "Region": "IledeFrance",
  "Date": "2017-7",
  "Consommation": 665858451,
  "Production": 36966405,
  "Thermique": 24751552,
  "Nucleaire": 0,
  "Eolien": 459322,
  "Solaire": 626469,
  "Hydraulique": 470854,
  "BioEnergie": 10658208
 },
 {
  "Region": "IledeFrance",
  "Date": "2017-8",
  "Consommation": 674543564,
  "Production": 37215077,
  "Thermique": 24757652,
  "Nucleaire": 0,
  "Eolien": 470126,
  "Solaire": 644006,
  "Hydraulique": 477703,
  "BioEnergie": 10865590
 },
 {
  "Region": "IledeFrance",
  "Date": "2017-9",
  "Consommation": 684348103,
  "Production": 37498446,
  "Thermique": 24772786,
  "Nucleaire": 0,
  "Eolien": 486151,
  "Solaire": 657698,
  "Hydraulique": 484966,
  "BioEnergie": 11096845
 },
 {
  "Region": "IledeFrance",
  "Date": "2017-10",
  "Consommation": 695250596,
  "Production": 37839993,
  "Thermique": 24866598,
  "Nucleaire": 0,
  "Eolien": 503161,
  "Solaire": 667993,
  "Hydraulique": 493606,
  "BioEnergie": 11308635
 },
 {
  "Region": "IledeFrance",
  "Date": "2017-11",
  "Consommation": 708727970,
  "Production": 38986513,
  "Thermique": 25755723,
  "Nucleaire": 0,
  "Eolien": 524664,
  "Solaire": 673287,
  "Hydraulique": 501865,
  "BioEnergie": 11530974
 },
 {
  "Region": "IledeFrance",
  "Date": "2017-12",
  "Consommation": 724076070,
  "Production": 40095036,
  "Thermique": 26595155,
  "Nucleaire": 0,
  "Eolien": 554915,
  "Solaire": 676047,
  "Hydraulique": 511505,
  "BioEnergie": 11757414
 },
 {
  "Region": "IledeFrance",
  "Date": "2017",
  "Consommation": 76531010001,
  "Production": 4756666049,
  "Thermique": 3460930401,
  "Nucleaire": 0,
  "Eolien": 40524059,
  "Solaire": 63372942,
  "Hydraulique": 41013331,
  "BioEnergie": 1150825316
 },
 {
  "Region": "IledeFrance",
  "Date": "2018-1",
  "Consommation": 738199294,
  "Production": 40913765,
  "Thermique": 27156764,
  "Nucleaire": 0,
  "Eolien": 592371,
  "Solaire": 677915,
  "Hydraulique": 512030,
  "BioEnergie": 11974685
 },
 {
  "Region": "IledeFrance",
  "Date": "2018-2",
  "Consommation": 753583263,
  "Production": 41837471,
  "Thermique": 27850737,
  "Nucleaire": 0,
  "Eolien": 616263,
  "Solaire": 685475,
  "Hydraulique": 512030,
  "BioEnergie": 12172966
 },
 {
  "Region": "IledeFrance",
  "Date": "2018-3",
  "Consommation": 768473699,
  "Production": 42842901,
  "Thermique": 28603941,
  "Nucleaire": 0,
  "Eolien": 643199,
  "Solaire": 695811,
  "Hydraulique": 512034,
  "BioEnergie": 12387916
 },
 {
  "Region": "IledeFrance",
  "Date": "2018-4",
  "Consommation": 779070190,
  "Production": 43089623,
  "Thermique": 28611937,
  "Nucleaire": 0,
  "Eolien": 660267,
  "Solaire": 712767,
  "Hydraulique": 514064,
  "BioEnergie": 12590588
 },
 {
  "Region": "IledeFrance",
  "Date": "2018-5",
  "Consommation": 789088169,
  "Production": 43353586,
  "Thermique": 28617579,
  "Nucleaire": 0,
  "Eolien": 675993,
  "Solaire": 736553,
  "Hydraulique": 526132,
  "BioEnergie": 12797329
 },
 {
  "Region": "IledeFrance",
  "Date": "2018-6",
  "Consommation": 798620567,
  "Production": 43611574,
  "Thermique": 28625313,
  "Nucleaire": 0,
  "Eolien": 687396,
  "Solaire": 758343,
  "Hydraulique": 537922,
  "BioEnergie": 13002600
 },
 {
  "Region": "IledeFrance",
  "Date": "2018-7",
  "Consommation": 808424189,
  "Production": 43910574,
  "Thermique": 28639992,
  "Nucleaire": 0,
  "Eolien": 696800,
  "Solaire": 783148,
  "Hydraulique": 548114,
  "BioEnergie": 13242520
 },
 {
  "Region": "IledeFrance",
  "Date": "2018-8",
  "Consommation": 817199093,
  "Production": 44195429,
  "Thermique": 28669202,
  "Nucleaire": 0,
  "Eolien": 709939,
  "Solaire": 804446,
  "Hydraulique": 556822,
  "BioEnergie": 13455020
 },
 {
  "Region": "IledeFrance",
  "Date": "2018-9",
  "Consommation": 826587217,
  "Production": 44438443,
  "Thermique": 28673589,
  "Nucleaire": 0,
  "Eolien": 725016,
  "Solaire": 822894,
  "Hydraulique": 563588,
  "BioEnergie": 13653356
 },
 {
  "Region": "IledeFrance",
  "Date": "2018-10",
  "Consommation": 837655334,
  "Production": 44713748,
  "Thermique": 28698485,
  "Nucleaire": 0,
  "Eolien": 745547,
  "Solaire": 839436,
  "Hydraulique": 571522,
  "BioEnergie": 13858758
 },
 {
  "Region": "IledeFrance",
  "Date": "2018-11",
  "Consommation": 851172052,
  "Production": 45673122,
  "Thermique": 29404315,
  "Nucleaire": 0,
  "Eolien": 767058,
  "Solaire": 849158,
  "Hydraulique": 579307,
  "BioEnergie": 14073284
 },
 {
  "Region": "IledeFrance",
  "Date": "2018-12",
  "Consommation": 865670030,
  "Production": 46647321,
  "Thermique": 30102568,
  "Nucleaire": 0,
  "Eolien": 797533,
  "Solaire": 850924,
  "Hydraulique": 592649,
  "BioEnergie": 14303647
 },
 {
  "Region": "IledeFrance",
  "Date": "2018",
  "Consommation": 162695763099,
  "Production": 10038559655,
  "Thermique": 7265515224,
  "Nucleaire": 0,
  "Eolien": 89365500,
  "Solaire": 135962754,
  "Hydraulique": 88552876,
  "BioEnergie": 2459163301
 },
 {
  "Region": "IledeFrance",
  "Date": "2019-1",
  "Consommation": 881847225,
  "Production": 47689008,
  "Thermique": 30879697,
  "Nucleaire": 0,
  "Eolien": 819321,
  "Solaire": 856415,
  "Hydraulique": 605149,
  "BioEnergie": 14528426
 },
 {
  "Region": "IledeFrance",
  "Date": "2019-2",
  "Consommation": 895117497,
  "Production": 48527131,
  "Thermique": 31476750,
  "Nucleaire": 0,
  "Eolien": 837793,
  "Solaire": 868304,
  "Hydraulique": 617227,
  "BioEnergie": 14727057
 },
 {
  "Region": "IledeFrance",
  "Date": "2019-3",
  "Consommation": 907983105,
  "Production": 49338177,
  "Thermique": 32008124,
  "Nucleaire": 0,
  "Eolien": 876226,
  "Solaire": 884842,
  "Hydraulique": 631930,
  "BioEnergie": 14937055
 },
 {
  "Region": "IledeFrance",
  "Date": "2019-4",
  "Consommation": 918958650,
  "Production": 49562723,
  "Thermique": 32013642,
  "Nucleaire": 0,
  "Eolien": 895676,
  "Solaire": 903722,
  "Hydraulique": 646257,
  "BioEnergie": 15103426
 },
 {
  "Region": "IledeFrance",
  "Date": "2019-5",
  "Consommation": 929495307,
  "Production": 49814689,
  "Thermique": 32015862,
  "Nucleaire": 0,
  "Eolien": 916439,
  "Solaire": 927231,
  "Hydraulique": 660490,
  "BioEnergie": 15294667
 },
 {
  "Region": "IledeFrance",
  "Date": "2019-6",
  "Consommation": 938986252,
  "Production": 50050956,
  "Thermique": 32017997,
  "Nucleaire": 0,
  "Eolien": 934368,
  "Solaire": 952690,
  "Hydraulique": 670021,
  "BioEnergie": 15475880
 },
 {
  "Region": "IledeFrance",
  "Date": "2019-7",
  "Consommation": 948496085,
  "Production": 50361300,
  "Thermique": 32051681,
  "Nucleaire": 0,
  "Eolien": 952929,
  "Solaire": 980266,
  "Hydraulique": 676707,
  "BioEnergie": 15699717
 },
 {
  "Region": "IledeFrance",
  "Date": "2019-8",
  "Consommation": 956884168,
  "Production": 50643089,
  "Thermique": 32079018,
  "Nucleaire": 0,
  "Eolien": 977349,
  "Solaire": 1004610,
  "Hydraulique": 681045,
  "BioEnergie": 15901067
 },
 {
  "Region": "IledeFrance",
  "Date": "2019-9",
  "Consommation": 965951245,
  "Production": 50934606,
  "Thermique": 32113384,
  "Nucleaire": 0,
  "Eolien": 1016653,
  "Solaire": 1027602,
  "Hydraulique": 687946,
  "BioEnergie": 16089021
 },
 {
  "Region": "IledeFrance",
  "Date": "2019-10",
  "Consommation": 977040871,
  "Production": 51313120,
  "Thermique": 32217479,
  "Nucleaire": 0,
  "Eolien": 1062718,
  "Solaire": 1042405,
  "Hydraulique": 697779,
  "BioEnergie": 16292739
 },
 {
  "Region": "IledeFrance",
  "Date": "2019-11",
  "Consommation": 990492622,
  "Production": 52277566,
  "Thermique": 32912104,
  "Nucleaire": 0,
  "Eolien": 1108465,
  "Solaire": 1051666,
  "Hydraulique": 710276,
  "BioEnergie": 16495055
 },
 {
  "Region": "IledeFrance",
  "Date": "2019-12",
  "Consommation": 1004885326,
  "Production": 53126748,
  "Thermique": 33489726,
  "Nucleaire": 0,
  "Eolien": 1167646,
  "Solaire": 1060456,
  "Hydraulique": 716420,
  "BioEnergie": 16692500
 },
 {
  "Region": "IledeFrance",
  "Date": "2019",
  "Consommation": 336707664551,
  "Production": 20680758423,
  "Thermique": 14916305912,
  "Nucleaire": 0,
  "Eolien": 190296583,
  "Solaire": 283485717,
  "Hydraulique": 185106999,
  "BioEnergie": 5105563212
 },
 {
  "Region": "IledeFrance",
  "Date": "2020-1",
  "Consommation": 1019967091,
  "Production": 53914873,
  "Thermique": 34010187,
  "Nucleaire": 0,
  "Eolien": 1220848,
  "Solaire": 1068030,
  "Hydraulique": 724792,
  "BioEnergie": 16891016
 },
 {
  "Region": "IledeFrance",
  "Date": "2020-2",
  "Consommation": 1032826011,
  "Production": 54598027,
  "Thermique": 34444315,
  "Nucleaire": 0,
  "Eolien": 1295973,
  "Solaire": 1079326,
  "Hydraulique": 728198,
  "BioEnergie": 17050215
 },
 {
  "Region": "IledeFrance",
  "Date": "2020-3",
  "Consommation": 1045216554,
  "Production": 55453202,
  "Thermique": 35012572,
  "Nucleaire": 0,
  "Eolien": 1355326,
  "Solaire": 1097396,
  "Hydraulique": 730143,
  "BioEnergie": 17257765
 },
 {
  "Region": "IledeFrance",
  "Date": "2020-4",
  "Consommation": 1053750392,
  "Production": 55723642,
  "Thermique": 35015289,
  "Nucleaire": 0,
  "Eolien": 1386249,
  "Solaire": 1124117,
  "Hydraulique": 741237,
  "BioEnergie": 17456750
 },
 {
  "Region": "IledeFrance",
  "Date": "2020-5",
  "Consommation": 1062529921,
  "Production": 55996443,
  "Thermique": 35018333,
  "Nucleaire": 0,
  "Eolien": 1421055,
  "Solaire": 1156878,
  "Hydraulique": 751522,
  "BioEnergie": 17648655
 },
 {
  "Region": "IledeFrance",
  "Date": "2020-6",
  "Consommation": 1071321879,
  "Production": 56418916,
  "Thermique": 35168435,
  "Nucleaire": 0,
  "Eolien": 1446761,
  "Solaire": 1186057,
  "Hydraulique": 758105,
  "BioEnergie": 17859558
 },
 {
  "Region": "IledeFrance",
  "Date": "2020-7",
  "Consommation": 1080138673,
  "Production": 56935119,
  "Thermique": 35385353,
  "Nucleaire": 0,
  "Eolien": 1474474,
  "Solaire": 1222410,
  "Hydraulique": 763749,
  "BioEnergie": 18089133
 },
 {
  "Region": "IledeFrance",
  "Date": "2020-8",
  "Consommation": 1088737313,
  "Production": 57279439,
  "Thermique": 35461260,
  "Nucleaire": 0,
  "Eolien": 1502634,
  "Solaire": 1257154,
  "Hydraulique": 768805,
  "BioEnergie": 18289586
 },
 {
  "Region": "IledeFrance",
  "Date": "2020-9",
  "Consommation": 1097928263,
  "Production": 57758909,
  "Thermique": 35640128,
  "Nucleaire": 0,
  "Eolien": 1533665,
  "Solaire": 1286706,
  "Hydraulique": 774037,
  "BioEnergie": 18524373
 },
 {
  "Region": "IledeFrance",
  "Date": "2020-10",
  "Consommation": 1109137633,
  "Production": 57999392,
  "Thermique": 35649078,
  "Nucleaire": 0,
  "Eolien": 1594666,
  "Solaire": 1302771,
  "Hydraulique": 783875,
  "BioEnergie": 18669002
 },
 {
  "Region": "IledeFrance",
  "Date": "2020-11",
  "Consommation": 1120871713,
  "Production": 58749125,
  "Thermique": 36176338,
  "Nucleaire": 0,
  "Eolien": 1633976,
  "Solaire": 1315949,
  "Hydraulique": 794115,
  "BioEnergie": 18828747
 },
 {
  "Region": "IledeFrance",
  "Date": "2020-12",
  "Consommation": 1134895064,
  "Production": 59831277,
  "Thermique": 37000818,
  "Nucleaire": 0,
  "Eolien": 1698537,
  "Solaire": 1323484,
  "Hydraulique": 802321,
  "BioEnergie": 19006117
 },
 {
  "Region": "IledeFrance",
  "Date": "2020",
  "Consommation": 686332649609,
  "Production": 42042175210,
  "Thermique": 30256593930,
  "Nucleaire": 0,
  "Eolien": 398157330,
  "Solaire": 581391712,
  "Hydraulique": 379334897,
  "BioEnergie": 10426697341
 },
 {
  "Region": "IledeFrance",
  "Date": "2021-1",
  "Consommation": 1150503911,
  "Production": 60917826,
  "Thermique": 37819152,
  "Nucleaire": 0,
  "Eolien": 1751542,
  "Solaire": 1329512,
  "Hydraulique": 807798,
  "BioEnergie": 19209822
 },
 {
  "Region": "IledeFrance",
  "Date": "2021-2",
  "Consommation": 1163294343,
  "Production": 61784446,
  "Thermique": 38432064,
  "Nucleaire": 0,
  "Eolien": 1808371,
  "Solaire": 1343809,
  "Hydraulique": 808921,
  "BioEnergie": 19391281
 },
 {
  "Region": "IledeFrance",
  "Date": "2021-3",
  "Consommation": 1176210124,
  "Production": 62624327,
  "Thermique": 38993014,
  "Nucleaire": 0,
  "Eolien": 1858056,
  "Solaire": 1357512,
  "Hydraulique": 822019,
  "BioEnergie": 19593726
 },
 {
  "Region": "IledeFrance",
  "Date": "2021-4",
  "Consommation": 1187347045,
  "Production": 62982697,
  "Thermique": 39056784,
  "Nucleaire": 0,
  "Eolien": 1900394,
  "Solaire": 1396179,
  "Hydraulique": 834897,
  "BioEnergie": 19794443
 },
 {
  "Region": "IledeFrance",
  "Date": "2021-5",
  "Consommation": 1197553227,
  "Production": 63316713,
  "Thermique": 39098166,
  "Nucleaire": 0,
  "Eolien": 1958618,
  "Solaire": 1433895,
  "Hydraulique": 850446,
  "BioEnergie": 19975588
 },
 {
  "Region": "IledeFrance",
  "Date": "2021-6",
  "Consommation": 1206622881,
  "Production": 63593360,
  "Thermique": 39125532,
  "Nucleaire": 0,
  "Eolien": 1973462,
  "Solaire": 1471772,
  "Hydraulique": 864351,
  "BioEnergie": 20158243
 },
 {
  "Region": "IledeFrance",
  "Date": "2021-7",
  "Consommation": 1215408058,
  "Production": 63904962,
  "Thermique": 39127669,
  "Nucleaire": 0,
  "Eolien": 2004877,
  "Solaire": 1510181,
  "Hydraulique": 873704,
  "BioEnergie": 20388531
 },
 {
  "Region": "IledeFrance",
  "Date": "2021-8",
  "Consommation": 1223393292,
  "Production": 64145509,
  "Thermique": 39137891,
  "Nucleaire": 0,
  "Eolien": 2030602,
  "Solaire": 1541170,
  "Hydraulique": 875198,
  "BioEnergie": 20560648
 },
 {
  "Region": "IledeFrance",
  "Date": "2021-9",
  "Consommation": 1232467420,
  "Production": 64457926,
  "Thermique": 39142504,
  "Nucleaire": 0,
  "Eolien": 2056424,
  "Solaire": 1580351,
  "Hydraulique": 881207,
  "BioEnergie": 20797440
 },
 {
  "Region": "IledeFrance",
  "Date": "2021-10",
  "Consommation": 1243415617,
  "Production": 64863352,
  "Thermique": 39210012,
  "Nucleaire": 0,
  "Eolien": 2113026,
  "Solaire": 1609731,
  "Hydraulique": 891834,
  "BioEnergie": 21038749
 },
 {
  "Region": "IledeFrance",
  "Date": "2021-11",
  "Consommation": 1256885345,
  "Production": 65974666,
  "Thermique": 40040475,
  "Nucleaire": 0,
  "Eolien": 2159146,
  "Solaire": 1623265,
  "Hydraulique": 902806,
  "BioEnergie": 21248974
 },
 {
  "Region": "IledeFrance",
  "Date": "2021-12",
  "Consommation": 1271405406,
  "Production": 67112293,
  "Thermique": 40890289,
  "Nucleaire": 0,
  "Eolien": 2227441,
  "Solaire": 1632363,
  "Hydraulique": 912314,
  "BioEnergie": 21449886
 },
 {
  "Region": "IledeFrance",
  "Date": "2021",
  "Consommation": 1387189805887,
  "Production": 84850028497,
  "Thermique": 60983261412,
  "Nucleaire": 0,
  "Eolien": 820156619,
  "Solaire": 1180613164,
  "Hydraulique": 768995289,
  "BioEnergie": 21097002013
 }
]}